openSheild/__init__.py
openSheild/mesh.py
openSheild/tally.py
openSheild-1.0.2.dist-info/LICENSE
openSheild-1.0.2.dist-info/METADATA
openSheild-1.0.2.dist-info/WHEEL
openSheild-1.0.2.dist-info/top_level.txt
openSheild-1.0.2.dist-info/RECORD
